{
    "msg": "",
    "flag": 200,
    "list": [
        {
           
            "orderId": "662428059737587712",
            "remark": "武威景煜图文文印店",
            "createOn": "2017-11-06"
        },
        {
            
            "orderId": "442420085863579648",
            "remark": "武威凉州区惠优房屋中介",
            "createOn": "2017-10-31"
        },
        {
            "amount": -2400,
            "orderId": "442414054450659328",
            "remark": "武威凉州区惠优房屋中介",
            "createOn": "2017-10-27"
        },
        {
            "amount": 1600,
            "orderId": "442414054282002432",
            "remark": "武威凉州区惠优房屋中介",
            "createOn": "2017-10-27"
        },
        {
            "amount": 0.39,
            "orderId": "662398058920902656",
            "remark": "商城",
            "createOn": "2017-10-26"
        },
        {
            "amount": 2400,
            "orderId": "442411373048643584",
            "remark": "武威凉州区惠优房屋中介",
            "createOn": "2017-10-25"
        },
        {
            "amount": 0.46,
            "orderId": "662397325237387264",
            "remark": "商城",
            "createOn": "2017-10-21"
        },
        {
            "amount": 0.59,
            "orderId": "662397289679159296",
            "remark": "商城",
            "createOn": "2017-10-21"
        },
        {
            "amount": 0.8,
            "orderId": "662399713448558592",
            "remark": "开阳商务宾馆",
            "createOn": "2017-10-17"
        },
        {
            "amount": 4,
            "orderId": "662399658663002112",
            "remark": "武威景煜图文文印店",
            "createOn": "2017-10-17"
        },
        {
            "amount": 17.6,
            "orderId": "662399651631251456",
            "remark": "武威景煜图文文印店",
            "createOn": "2017-10-17"
        },
        {
            "amount": 1.6,
            "orderId": "662396978640650240",
            "remark": "开阳商务宾馆",
            "createOn": "2017-10-15"
        },
        {
            "amount": 0.02,
            "orderId": "662396941321191424",
            "remark": "开阳商务宾馆",
            "createOn": "2017-10-15"
        }
    ]
}